{
  "_class": "symbolMaster",
  "backgroundColor": {
    "_class": "color",
    "alpha": 1,
    "blue": 1,
    "green": 1,
    "red": 1
  },
  "changeIdentifier": 5785,
  "do_objectID": "90285619-2E36-431B-93EC-EE644FEAB28B",
  "exportOptions": {
    "_class": "exportOptions",
    "exportFormats": [
    ],
    "includedLayerIds": [
    ],
    "layerOptions": 0,
    "shouldTrim": false
  },
  "frame": {
    "_class": "rect",
    "constrainProportions": false,
    "height": 55,
    "width": 900,
    "x": 600,
    "y": 0
  },
  "hasBackgroundColor": false,
  "hasClickThrough": false,
  "horizontalRulerData": {
    "_class": "rulerData",
    "base": 0,
    "guides": [
    ]
  },
  "includeBackgroundColorInExport": true,
  "includeBackgroundColorInInstance": false,
  "includeInCloudUpload": true,
  "isFlippedHorizontal": false,
  "isFlippedVertical": false,
  "isFlowHome": false,
  "isLocked": false,
  "isVisible": true,
  "layerListExpandedType": 0,
  "layers": [
    {
      "class": "shapeGroup",
      "id": "16E91092-2D67-4776-AE28-6ED9EB006094"
    },
    {
      "class": "symbolInstance",
      "id": "113C2ABC-6C5F-486A-9CD4-8C4BCF9DE470"
    },
    {
      "class": "text",
      "id": "CD54E9C9-A481-4FB3-8058-994234619F15"
    },
    {
      "class": "group",
      "id": "ADF104C0-159C-465C-8179-A37EFEA84F7F"
    }
  ],
  "name": "Header",
  "nameIsFixed": false,
  "resizesContent": true,
  "resizingConstraint": 63,
  "resizingType": 0,
  "rotation": 0,
  "shouldBreakMaskChain": true,
  "style": {
    "_class": "style",
    "endDecorationType": 0,
    "miterLimit": 10,
    "startDecorationType": 0
  },
  "symbolID": "92023F60-F89E-4231-ACEB-78C4CC0CE1DA",
  "verticalRulerData": {
    "_class": "rulerData",
    "base": 0,
    "guides": [
    ]
  }
}