{
  "_class": "shapePath",
  "booleanOperation": -1,
  "do_objectID": "10EF8E5B-823C-4848-9D3E-160063B08231",
  "edited": true,
  "exportOptions": {
    "_class": "exportOptions",
    "do_objectID": "B0D97AB9-8AAB-4119-B72C-8C92A9B98917",
    "exportFormats": [
    ],
    "includedLayerIds": [
    ],
    "layerOptions": 0,
    "shouldTrim": false
  },
  "frame": {
    "_class": "rect",
    "constrainProportions": false,
    "do_objectID": "9ED37EBC-1994-4EB4-9A94-ED360F3CD07E",
    "height": 1.357142857142836,
    "width": 1.781452437777066,
    "x": 19.38754688032765,
    "y": 24.87100000000012
  },
  "isClosed": true,
  "isFlippedHorizontal": false,
  "isFlippedVertical": false,
  "isLocked": false,
  "isVisible": true,
  "layerListExpandedType": 0,
  "name": "bq-path",
  "nameIsFixed": false,
  "path": {
    "_class": "path",
    "isClosed": true,
    "pointRadiusBehaviour": 1,
    "points": [
      {
        "_class": "curvePoint",
        "cornerRadius": 0,
        "curveFrom": "{0, 0.22299999999999898}",
        "curveMode": 1,
        "curveTo": "{0, 0.22299999999999898}",
        "hasCurveFrom": false,
        "hasCurveTo": false,
        "point": "{0, 0.22299999999999898}"
      },
      {
        "_class": "curvePoint",
        "cornerRadius": 0,
        "curveFrom": "{0.41499999999999915, 0.50300000000000011}",
        "curveMode": 1,
        "curveTo": "{0.41499999999999915, 0.50300000000000011}",
        "hasCurveFrom": false,
        "hasCurveTo": false,
        "point": "{0.41499999999999915, 0.50300000000000011}"
      },
      {
        "_class": "curvePoint",
        "cornerRadius": 0,
        "curveFrom": "{0.5779999999999994, 0.26099999999999923}",
        "curveMode": 1,
        "curveTo": "{0.5779999999999994, 0.26099999999999923}",
        "hasCurveFrom": false,
        "hasCurveTo": false,
        "point": "{0.5779999999999994, 0.26099999999999923}"
      },
      {
        "_class": "curvePoint",
        "cornerRadius": 0,
        "curveFrom": "{0.44799999999999862, 0}",
        "curveMode": 1,
        "curveTo": "{0.44799999999999862, 0}",
        "hasCurveFrom": false,
        "hasCurveTo": false,
        "point": "{0.44799999999999862, 0}"
      },
      {
        "_class": "curvePoint",
        "cornerRadius": 0,
        "curveFrom": "{0.00099999999999944578, 0.22299999999999898}",
        "curveMode": 1,
        "curveTo": "{0.00099999999999944578, 0.22299999999999898}",
        "hasCurveFrom": false,
        "hasCurveTo": false,
        "point": "{0.00099999999999944578, 0.22299999999999898}"
      }
    ]
  },
  "pointRadiusBehaviour": 1,
  "points": [
    {
      "_class": "curvePoint",
      "cornerRadius": 0,
      "curveFrom": "{0, 0.22299999999999898}",
      "curveMode": 1,
      "curveTo": "{0, 0.22299999999999898}",
      "hasCurveFrom": false,
      "hasCurveTo": false,
      "point": "{0, 0.22299999999999898}"
    },
    {
      "_class": "curvePoint",
      "cornerRadius": 0,
      "curveFrom": "{0.41499999999999915, 0.50300000000000011}",
      "curveMode": 1,
      "curveTo": "{0.41499999999999915, 0.50300000000000011}",
      "hasCurveFrom": false,
      "hasCurveTo": false,
      "point": "{0.41499999999999915, 0.50300000000000011}"
    },
    {
      "_class": "curvePoint",
      "cornerRadius": 0,
      "curveFrom": "{0.5779999999999994, 0.26099999999999923}",
      "curveMode": 1,
      "curveTo": "{0.5779999999999994, 0.26099999999999923}",
      "hasCurveFrom": false,
      "hasCurveTo": false,
      "point": "{0.5779999999999994, 0.26099999999999923}"
    },
    {
      "_class": "curvePoint",
      "cornerRadius": 0,
      "curveFrom": "{0.44799999999999862, 0}",
      "curveMode": 1,
      "curveTo": "{0.44799999999999862, 0}",
      "hasCurveFrom": false,
      "hasCurveTo": false,
      "point": "{0.44799999999999862, 0}"
    },
    {
      "_class": "curvePoint",
      "cornerRadius": 0,
      "curveFrom": "{0.00099999999999944578, 0.22299999999999898}",
      "curveMode": 1,
      "curveTo": "{0.00099999999999944578, 0.22299999999999898}",
      "hasCurveFrom": false,
      "hasCurveTo": false,
      "point": "{0.00099999999999944578, 0.22299999999999898}"
    }
  ],
  "resizingConstraint": 63,
  "resizingType": 0,
  "rotation": 0,
  "shouldBreakMaskChain": false
}