{
  "_class": "symbolMaster",
  "backgroundColor": {
    "_class": "color",
    "alpha": 1,
    "blue": 1,
    "do_objectID": "BE34504F-930E-4624-9C13-02C3AD66EB35",
    "green": 1,
    "red": 1
  },
  "changeIdentifier": 980,
  "do_objectID": "1F923E36-EC74-4E3D-801E-FEA4C0224B55",
  "exportOptions": {
    "_class": "exportOptions",
    "do_objectID": "EF10A198-EF01-4736-96FC-2C9C68319255",
    "exportFormats": [
    ],
    "includedLayerIds": [
    ],
    "layerOptions": 0,
    "shouldTrim": false
  },
  "frame": {
    "_class": "rect",
    "constrainProportions": false,
    "do_objectID": "B80ABBC3-7075-4982-9268-0CEABF71A1EC",
    "height": 40,
    "width": 146,
    "x": 560,
    "y": 120
  },
  "hasBackgroundColor": false,
  "hasClickThrough": true,
  "horizontalRulerData": {
    "_class": "rulerData",
    "base": 0,
    "do_objectID": "9D43E6C0-2DB0-4BB3-812C-D3B0C98ADF58",
    "guides": [
    ]
  },
  "includeBackgroundColorInExport": true,
  "includeBackgroundColorInInstance": false,
  "includeInCloudUpload": true,
  "isFlippedHorizontal": false,
  "isFlippedVertical": false,
  "isFlowHome": false,
  "isLocked": false,
  "isVisible": true,
  "layerListExpandedType": 2,
  "layers": [
    {
      "class": "shapeGroup",
      "id": "F54B987E-7618-43EE-BAD2-38AACEEB69F6"
    },
    {
      "class": "shapeGroup",
      "id": "D73CF0E8-E3B5-4857-93A0-646B2F53C98E"
    },
    {
      "class": "text",
      "id": "11132BE3-4AE4-4DFF-BC10-0369D6907E4E"
    },
    {
      "class": "symbolInstance",
      "id": "F990E3F0-A599-4994-B4D3-3006FED27D8A"
    }
  ],
  "name": "atom/button/label/focus",
  "nameIsFixed": true,
  "resizesContent": true,
  "resizingConstraint": 63,
  "resizingType": 0,
  "rotation": 0,
  "shouldBreakMaskChain": true,
  "style": {
    "_class": "style",
    "do_objectID": "0036B09E-A473-4570-9869-F07C7CC977E4",
    "endDecorationType": 0,
    "miterLimit": 10,
    "startDecorationType": 0
  },
  "symbolID": "68FB3BD5-0F5D-47D0-953F-AC217EFEDDAC",
  "verticalRulerData": {
    "_class": "rulerData",
    "base": 0,
    "do_objectID": "B77E9535-5A02-4E11-9FA3-2BCF8409E538",
    "guides": [
    ]
  }
}