{
  "_class": "group",
  "do_objectID": "67BD1FA6-4BBC-43EF-9CCB-22D1101CE4D5",
  "exportOptions": {
    "_class": "exportOptions",
    "do_objectID": "CF334CE7-D335-458C-A640-65D13952F6AB",
    "exportFormats": [
    ],
    "includedLayerIds": [
    ],
    "layerOptions": 0,
    "shouldTrim": false
  },
  "frame": {
    "_class": "rect",
    "constrainProportions": false,
    "do_objectID": "8F843129-9EF9-4540-AB51-CA1034E091AB",
    "height": 29,
    "width": 30,
    "x": 269.3556085918856,
    "y": 32
  },
  "hasClickThrough": false,
  "isFlippedHorizontal": false,
  "isFlippedVertical": false,
  "isLocked": false,
  "isVisible": true,
  "layerListExpandedType": 0,
  "layers": [
    {
      "class": "shapeGroup",
      "id": "65D73964-393B-4C91-8FBC-7A2C326F5BB9"
    }
  ],
  "name": "aW-link",
  "nameIsFixed": false,
  "resizingConstraint": 63,
  "resizingType": 0,
  "rotation": 0,
  "shouldBreakMaskChain": false,
  "style": {
    "_class": "style",
    "contextSettings": {
      "_class": "graphicsContextSettings",
      "blendMode": 0,
      "do_objectID": "5D2E68A4-E5BD-4011-A998-6CA39ADD05F2",
      "opacity": 0.542
    },
    "do_objectID": "A2C38493-E617-4840-AE73-4F4A209BD491",
    "endDecorationType": 0,
    "fills": [
      {
        "_class": "fill",
        "color": {
          "_class": "color",
          "alpha": 1,
          "blue": 0,
          "green": 0,
          "red": 0
        },
        "fillType": 1,
        "gradient": {
          "_class": "gradient",
          "elipseLength": 0,
          "from": "{0.025270916334661355, 0}",
          "gradientType": 0,
          "stops": [
            {
              "_class": "gradientStop",
              "color": {
                "_class": "color",
                "alpha": 1,
                "blue": 0.7843137254901961,
                "green": 0.7843137254901961,
                "red": 0.7843137254901961
              },
              "position": 0
            },
            {
              "_class": "gradientStop",
              "color": {
                "_class": "color",
                "alpha": 1,
                "blue": 0.592156862745098,
                "green": 0.592156862745098,
                "red": 0.592156862745098
              },
              "position": 1
            }
          ],
          "to": "{0.025270916334661355, 0.10333412969283277}"
        },
        "isEnabled": true,
        "noiseIndex": 0,
        "noiseIntensity": 0,
        "patternFillType": 1,
        "patternTileScale": 1
      }
    ],
    "miterLimit": 10,
    "startDecorationType": 0
  }
}