{
  "_class": "shapeGroup",
  "clippingMaskMode": 0,
  "do_objectID": "C3002F09-3D2E-4C80-9728-36BC9D75854C",
  "exportOptions": {
    "_class": "exportOptions",
    "do_objectID": "E0237EB3-DF2C-462B-946E-A24BC2106C8C",
    "exportFormats": [
    ],
    "includedLayerIds": [
    ],
    "layerOptions": 0,
    "shouldTrim": false
  },
  "frame": {
    "_class": "rect",
    "constrainProportions": false,
    "do_objectID": "DE6A48FC-C7AA-467D-BC01-5E10C6B286AF",
    "height": 40,
    "width": 138,
    "x": 0,
    "y": 0
  },
  "hasClickThrough": false,
  "hasClippingMask": false,
  "isFlippedHorizontal": false,
  "isFlippedVertical": false,
  "isLocked": false,
  "isVisible": true,
  "layerListExpandedType": 0,
  "layers": [
    {
      "class": "rectangle",
      "id": "F284F336-0BEC-4A19-B09D-E224E66DEA2B"
    }
  ],
  "name": "Rectangle",
  "nameIsFixed": false,
  "resizingConstraint": 63,
  "resizingType": 0,
  "rotation": 0,
  "shouldBreakMaskChain": false,
  "style": {
    "sharedObjectID": "5CD9354D-330E-47F9-A289-B7115C5A2F59"
  },
  "windingRule": 1
}