{
  "_class": "group",
  "do_objectID": "CC9159A9-F83E-4584-AD46-9E90572D5917",
  "exportOptions": {
    "_class": "exportOptions",
    "do_objectID": "6D258607-C3CA-4A36-8F08-254A0887F40D",
    "exportFormats": [
    ],
    "includedLayerIds": [
    ],
    "layerOptions": 0,
    "shouldTrim": false
  },
  "frame": {
    "_class": "rect",
    "constrainProportions": false,
    "do_objectID": "90F36E04-727F-4825-BB76-B9253DE41682",
    "height": 49,
    "width": 28,
    "x": 768,
    "y": 303
  },
  "hasClickThrough": false,
  "isFlippedHorizontal": false,
  "isFlippedVertical": false,
  "isLocked": false,
  "isVisible": true,
  "layerListExpandedType": 0,
  "layers": [
    {
      "class": "shapeGroup",
      "id": "64AFFA5B-D11C-4776-80E9-C3D414A72BBF"
    }
  ],
  "name": "ac-link",
  "nameIsFixed": false,
  "resizingConstraint": 63,
  "resizingType": 0,
  "rotation": 0,
  "shouldBreakMaskChain": false,
  "style": {
    "_class": "style",
    "do_objectID": "13097E82-C04A-44E7-9DEE-73DA37706948",
    "endDecorationType": 0,
    "fills": [
      {
        "_class": "fill",
        "color": {
          "_class": "color",
          "alpha": 1,
          "blue": 0,
          "green": 0,
          "red": 0
        },
        "fillType": 1,
        "gradient": {
          "_class": "gradient",
          "elipseLength": 0,
          "from": "{0.014326693227091633, 0}",
          "gradientType": 0,
          "stops": [
            {
              "_class": "gradientStop",
              "color": {
                "_class": "color",
                "alpha": 1,
                "blue": 0.7843137254901961,
                "green": 0.7843137254901961,
                "red": 0.7843137254901961
              },
              "position": 0
            },
            {
              "_class": "gradientStop",
              "color": {
                "_class": "color",
                "alpha": 1,
                "blue": 0.592156862745098,
                "green": 0.592156862745098,
                "red": 0.592156862745098
              },
              "position": 1
            }
          ],
          "to": "{0.014326693227091633, 0.11785938566552902}"
        },
        "isEnabled": true,
        "noiseIndex": 0,
        "noiseIntensity": 0,
        "patternFillType": 1,
        "patternTileScale": 1
      }
    ],
    "miterLimit": 10,
    "startDecorationType": 0
  }
}