{
  "_class": "symbolMaster",
  "backgroundColor": {
    "_class": "color",
    "alpha": 1,
    "blue": 0.5843137254901961,
    "green": 0.5843137254901961,
    "red": 0.5843137254901961
  },
  "changeIdentifier": 634,
  "do_objectID": "14F13500-C864-4B64-898E-9855829C7ED3",
  "exportOptions": {
    "_class": "exportOptions",
    "do_objectID": "13B04334-EC4C-40E8-AD50-1B6D610DE46A",
    "exportFormats": [
    ],
    "includedLayerIds": [
    ],
    "layerOptions": 0,
    "shouldTrim": false
  },
  "frame": {
    "_class": "rect",
    "constrainProportions": false,
    "do_objectID": "3DD21652-4F11-4868-8E62-D8CD8494527A",
    "height": 15,
    "width": 15,
    "x": 2696,
    "y": 1380
  },
  "hasBackgroundColor": true,
  "hasClickThrough": true,
  "horizontalRulerData": {
    "_class": "rulerData",
    "base": 0,
    "do_objectID": "D2021914-8C80-4802-8E50-7A4403C7D651",
    "guides": [
    ]
  },
  "includeBackgroundColorInExport": true,
  "includeBackgroundColorInInstance": false,
  "includeInCloudUpload": true,
  "isFlippedHorizontal": false,
  "isFlippedVertical": false,
  "isFlowHome": false,
  "isLocked": false,
  "isVisible": true,
  "layerListExpandedType": 1,
  "layers": [
    {
      "class": "shapeGroup",
      "id": "C95D4879-2D8C-4F28-889B-6392AC3BFBB4"
    }
  ],
  "name": "color/grey-4",
  "nameIsFixed": true,
  "resizesContent": false,
  "resizingConstraint": 63,
  "resizingType": 0,
  "rotation": 0,
  "shouldBreakMaskChain": true,
  "style": {
    "_class": "style",
    "do_objectID": "891F615E-9382-4273-BCA5-3DE9E6CA20EC",
    "endDecorationType": 0,
    "fills": [
      {
        "_class": "fill",
        "color": {
          "_class": "color",
          "alpha": 1,
          "blue": 1,
          "green": 1,
          "red": 1
        },
        "fillType": 0,
        "isEnabled": true,
        "noiseIndex": 0,
        "noiseIntensity": 0,
        "patternFillType": 1,
        "patternTileScale": 1
      }
    ],
    "miterLimit": 10,
    "startDecorationType": 0
  },
  "symbolID": "9AD74CE2-33A6-42C3-93E5-8B5599A42F47",
  "verticalRulerData": {
    "_class": "rulerData",
    "base": 0,
    "do_objectID": "273EBF71-DB1C-4402-8CAD-AC70FA007DCF",
    "guides": [
    ]
  }
}