{
  "_class": "group",
  "do_objectID": "0D875F6C-FCBC-4AC7-8A84-272034169676",
  "exportOptions": {
    "_class": "exportOptions",
    "exportFormats": [
    ],
    "includedLayerIds": [
    ],
    "layerOptions": 0,
    "shouldTrim": false
  },
  "frame": {
    "_class": "rect",
    "constrainProportions": false,
    "height": 74,
    "width": 903,
    "x": 0,
    "y": 0
  },
  "hasClickThrough": false,
  "isFlippedHorizontal": false,
  "isFlippedVertical": false,
  "isLocked": false,
  "isVisible": true,
  "layerListExpandedType": 0,
  "layers": [
    {
      "class": "symbolInstance",
      "id": "161CC69A-74B9-4998-8273-5E5788ADBD33"
    },
    {
      "class": "text",
      "id": "B27A5AF8-4C51-4A0E-8EA8-23813EA9450A"
    }
  ],
  "name": "Heading",
  "nameIsFixed": true,
  "resizingConstraint": 15,
  "resizingType": 0,
  "rotation": 0,
  "shouldBreakMaskChain": false,
  "style": {
    "_class": "style",
    "endDecorationType": 0,
    "miterLimit": 10,
    "startDecorationType": 0
  }
}