{
  "_class": "shapePath",
  "booleanOperation": -1,
  "do_objectID": "0305EA8B-17B0-49A7-8425-CDD96605A2AE",
  "edited": true,
  "exportOptions": {
    "_class": "exportOptions",
    "do_objectID": "B200FA5E-FBC7-4B11-84ED-925D76A5ABEF",
    "exportFormats": [
    ],
    "includedLayerIds": [
    ],
    "layerOptions": 0,
    "shouldTrim": false
  },
  "frame": {
    "_class": "rect",
    "constrainProportions": false,
    "do_objectID": "237FE430-77D5-4377-969A-86C939A05B76",
    "height": 1.36496350364958,
    "width": 1.833362310136096,
    "x": 233.7701948031421,
    "y": 25.90700729927011
  },
  "isClosed": true,
  "isFlippedHorizontal": false,
  "isFlippedVertical": false,
  "isLocked": false,
  "isVisible": true,
  "layerListExpandedType": 0,
  "name": "ao-path",
  "nameIsFixed": false,
  "path": {
    "_class": "path",
    "isClosed": true,
    "pointRadiusBehaviour": 1,
    "points": [
      {
        "_class": "curvePoint",
        "cornerRadius": 0,
        "curveFrom": "{0.20100000000000762, 0.73199999999999932}",
        "curveMode": 1,
        "curveTo": "{0.20100000000000762, 0.73199999999999932}",
        "hasCurveFrom": false,
        "hasCurveTo": false,
        "point": "{0.20100000000000762, 0.73199999999999932}"
      },
      {
        "_class": "curvePoint",
        "cornerRadius": 0,
        "curveFrom": "{0.69799999999999329, 0.6769999999999996}",
        "curveMode": 1,
        "curveTo": "{0.69799999999999329, 0.6769999999999996}",
        "hasCurveFrom": false,
        "hasCurveTo": false,
        "point": "{0.69799999999999329, 0.6769999999999996}"
      },
      {
        "_class": "curvePoint",
        "cornerRadius": 0,
        "curveFrom": "{0.62300000000000466, 0}",
        "curveMode": 1,
        "curveTo": "{0.62300000000000466, 0}",
        "hasCurveFrom": false,
        "hasCurveTo": false,
        "point": "{0.62300000000000466, 0}"
      },
      {
        "_class": "curvePoint",
        "cornerRadius": 0,
        "curveFrom": "{0, 0.27499999999999858}",
        "curveMode": 1,
        "curveTo": "{0, 0.27499999999999858}",
        "hasCurveFrom": false,
        "hasCurveTo": false,
        "point": "{0, 0.27499999999999858}"
      },
      {
        "_class": "curvePoint",
        "cornerRadius": 0,
        "curveFrom": "{0.20099999999999341, 0.73199999999999932}",
        "curveMode": 1,
        "curveTo": "{0.20099999999999341, 0.73199999999999932}",
        "hasCurveFrom": false,
        "hasCurveTo": false,
        "point": "{0.20099999999999341, 0.73199999999999932}"
      }
    ]
  },
  "pointRadiusBehaviour": 1,
  "points": [
    {
      "_class": "curvePoint",
      "cornerRadius": 0,
      "curveFrom": "{0.20100000000000762, 0.73199999999999932}",
      "curveMode": 1,
      "curveTo": "{0.20100000000000762, 0.73199999999999932}",
      "hasCurveFrom": false,
      "hasCurveTo": false,
      "point": "{0.20100000000000762, 0.73199999999999932}"
    },
    {
      "_class": "curvePoint",
      "cornerRadius": 0,
      "curveFrom": "{0.69799999999999329, 0.6769999999999996}",
      "curveMode": 1,
      "curveTo": "{0.69799999999999329, 0.6769999999999996}",
      "hasCurveFrom": false,
      "hasCurveTo": false,
      "point": "{0.69799999999999329, 0.6769999999999996}"
    },
    {
      "_class": "curvePoint",
      "cornerRadius": 0,
      "curveFrom": "{0.62300000000000466, 0}",
      "curveMode": 1,
      "curveTo": "{0.62300000000000466, 0}",
      "hasCurveFrom": false,
      "hasCurveTo": false,
      "point": "{0.62300000000000466, 0}"
    },
    {
      "_class": "curvePoint",
      "cornerRadius": 0,
      "curveFrom": "{0, 0.27499999999999858}",
      "curveMode": 1,
      "curveTo": "{0, 0.27499999999999858}",
      "hasCurveFrom": false,
      "hasCurveTo": false,
      "point": "{0, 0.27499999999999858}"
    },
    {
      "_class": "curvePoint",
      "cornerRadius": 0,
      "curveFrom": "{0.20099999999999341, 0.73199999999999932}",
      "curveMode": 1,
      "curveTo": "{0.20099999999999341, 0.73199999999999932}",
      "hasCurveFrom": false,
      "hasCurveTo": false,
      "point": "{0.20099999999999341, 0.73199999999999932}"
    }
  ],
  "resizingConstraint": 63,
  "resizingType": 0,
  "rotation": 0,
  "shouldBreakMaskChain": false
}