{
  "_class": "shapeGroup",
  "clippingMaskMode": 0,
  "do_objectID": "994487C2-7468-416E-9AD7-2A01B8F1FDA8",
  "exportOptions": {
    "_class": "exportOptions",
    "exportFormats": [
    ],
    "includedLayerIds": [
    ],
    "layerOptions": 0,
    "shouldTrim": false
  },
  "frame": {
    "_class": "rect",
    "constrainProportions": false,
    "height": 14.60463157894737,
    "width": 15.43022843504959,
    "x": 0.626164336856466,
    "y": 0.6804210526315806
  },
  "hasClickThrough": false,
  "hasClippingMask": false,
  "isFlippedHorizontal": false,
  "isFlippedVertical": false,
  "isLocked": false,
  "isVisible": true,
  "layerListExpandedType": 0,
  "layers": [
    {
      "class": "shapePath",
      "id": "BF3A9F10-FD30-43EF-A3A3-62648C58947A"
    },
    {
      "class": "shapePath",
      "id": "753C4D7B-C784-49A8-9213-3F9398FE3220"
    },
    {
      "class": "shapePath",
      "id": "E54F8D50-CD6E-4E88-8748-59AD30A5F0D4"
    }
  ],
  "name": "aa",
  "nameIsFixed": false,
  "resizingConstraint": 63,
  "resizingType": 0,
  "rotation": 0,
  "shouldBreakMaskChain": false,
  "style": {
    "_class": "style",
    "endDecorationType": 0,
    "fills": [
      {
        "_class": "fill",
        "color": {
          "_class": "color",
          "alpha": 1,
          "blue": 0,
          "green": 0,
          "red": 0
        },
        "fillType": 1,
        "gradient": {
          "_class": "gradient",
          "elipseLength": 0,
          "from": "{0.50018892163530571, 0.011070749005362396}",
          "gradientType": 0,
          "stops": [
            {
              "_class": "gradientStop",
              "color": {
                "_class": "color",
                "alpha": 1,
                "blue": 0.7843137254901961,
                "green": 0.7843137254901961,
                "red": 0.7843137254901961
              },
              "position": 0
            },
            {
              "_class": "gradientStop",
              "color": {
                "_class": "color",
                "alpha": 1,
                "blue": 0.592156862745098,
                "green": 0.592156862745098,
                "red": 0.592156862745098
              },
              "position": 1
            }
          ],
          "to": "{0.50018892163530571, 0.92665052182436725}"
        },
        "isEnabled": true,
        "noiseIndex": 0,
        "noiseIntensity": 0,
        "patternFillType": 1,
        "patternTileScale": 1
      }
    ],
    "miterLimit": 10,
    "startDecorationType": 0
  },
  "windingRule": 0
}