{
  "_class": "shapeGroup",
  "clippingMaskMode": 0,
  "do_objectID": "691D9CAD-7AEC-44B6-BB94-44E19FE5BEED",
  "exportOptions": {
    "_class": "exportOptions",
    "do_objectID": "7CE7CD3A-E814-4AB2-A1C5-4002EE845EA8",
    "exportFormats": [
    ],
    "includedLayerIds": [
    ],
    "layerOptions": 0,
    "shouldTrim": false
  },
  "frame": {
    "_class": "rect",
    "constrainProportions": false,
    "do_objectID": "7FF4C30F-24F5-477C-8172-299FBC3B244D",
    "height": 22,
    "width": 22,
    "x": 0,
    "y": 0
  },
  "hasClickThrough": false,
  "hasClippingMask": false,
  "isFlippedHorizontal": false,
  "isFlippedVertical": false,
  "isLocked": false,
  "isVisible": true,
  "layerListExpandedType": 1,
  "layers": [
    {
      "class": "rectangle",
      "id": "FB9EA846-2824-4D92-9936-518EEF6BC444"
    }
  ],
  "name": "Rectangle 3",
  "nameIsFixed": false,
  "resizingConstraint": 63,
  "resizingType": 0,
  "rotation": 0,
  "shouldBreakMaskChain": false,
  "style": {
    "_class": "style",
    "do_objectID": "3EABEBFE-D312-46C9-919B-0B796E692AE8",
    "endDecorationType": 0,
    "fills": [
      {
        "_class": "fill",
        "color": {
          "_class": "color",
          "alpha": 1,
          "blue": 0.196078431372549,
          "green": 0.1137254901960784,
          "red": 0.9058823529411765
        },
        "fillType": 0,
        "isEnabled": true,
        "noiseIndex": 0,
        "noiseIntensity": 0,
        "patternFillType": 1,
        "patternTileScale": 1
      }
    ],
    "miterLimit": 10,
    "sharedObjectID": "77C2A2AB-4F92-4D22-80E8-0BE7A1ABEBCA",
    "startDecorationType": 0
  },
  "windingRule": 1
}