{
  "_class": "sharedStyle",
  "do_objectID": "AF99DB5A-6C6F-41B3-AFA1-85F81EAEEE71",
  "name": "color/brand-4",
  "value": {
    "_class": "style",
    "endDecorationType": 0,
    "fills": [
      {
        "_class": "fill",
        "color": {
          "_class": "color",
          "alpha": 1,
          "blue": 1,
          "green": 0.8291702817278934,
          "red": 0.8135456123737373
        },
        "fillType": 0,
        "isEnabled": true,
        "noiseIndex": 0,
        "noiseIntensity": 0,
        "patternFillType": 1,
        "patternTileScale": 1
      }
    ],
    "miterLimit": 10,
    "sharedObjectID": "AF99DB5A-6C6F-41B3-AFA1-85F81EAEEE71",
    "startDecorationType": 0
  }
}